[
  {
    "dimension": "Core Communication Purpose",
    "value": "Requesting action, information, or feedback on a specific academic matter."
  },
  {
    "dimension": "Expected Level of Detail",
    "value": "Sufficient context provided to the professor without requiring extensive follow-up questions."
  },
  {
    "dimension": "Implicit Tone Nuance",
    "value": "Respectfully professional while acknowledging the established (familiar) working relationship."
  },
  {
    "dimension": "Actionability",
    "value": "Likely requires a specific response or action from the professor, not just an informational update from the student."
  },
  {
    "dimension": "Subject Matter Nature",
    "value": "Related to current academic work, research, or administrative tasks within the university structure."
  }
]