[
  {
    "dimension": "Core Email Topic",
    "value": "Academic progress update addressing a specific issue or delay"
  },
  {
    "dimension": "Reason for Apology",
    "value": "Likely related to a missed deadline, delay, mistake, or underperformance on a task"
  },
  {
    "dimension": "Purpose of Expressing Gratitude",
    "value": "Thanking the supervisor for past help, guidance, understanding, or opportunity despite the issue"
  },
  {
    "dimension": "Source of Excitement",
    "value": "Enthusiasm for recent progress, future plans, or continuing the work despite the setback"
  },
  {
    "dimension": "Underlying Communication Goal",
    "value": "Mitigate a negative situation while reaffirming commitment and appreciation"
  }
]