[
  {
    "dimension": "Stipend Request Approach",
    "current_value": "Direct with personal context",
    "other_values": [
      "Subtle suggestion, open-ended",
      "Formal request, minimal detail",
      "Propose alternative solutions"
    ]
  },
  {
    "dimension": "Justification for Extension",
    "current_value": "Personal family emergency",
    "other_values": [
      "Research-focused, project needs",
      "Combination personal and research",
      "Vague mention of difficulties"
    ]
  },
  {
    "dimension": "Tone Regarding Request",
    "current_value": "Grateful and appreciative",
    "other_values": [
      "Formal and business-like",
      "Urgent and stressed",
      "Hopeful and optimistic"
    ]
  },
  {
    "dimension": "Commitment Reassurance",
    "current_value": "Explicit and proactive",
    "other_values": [
      "Implied through past performance",
      "Offer to discuss work plan",
      "No explicit reassurance needed"
    ]
  }
]